platemapper/__init__.py
platemapper/_version.py
platemapper/napari.yaml
platemapper/platemapper.py
platemapper/_tests/__init__.py
platemapper/_tests/test_plate_mapper.py
platemapper-0.1.1.dist-info/LICENSE
platemapper-0.1.1.dist-info/METADATA
platemapper-0.1.1.dist-info/WHEEL
platemapper-0.1.1.dist-info/entry_points.txt
platemapper-0.1.1.dist-info/top_level.txt
platemapper-0.1.1.dist-info/RECORD
